README.md
setup.py
wok_serve/__init__.py
wok_serve/cli.py
wok_serve/server.py
wok_serve.egg-info/PKG-INFO
wok_serve.egg-info/SOURCES.txt
wok_serve.egg-info/dependency_links.txt
wok_serve.egg-info/entry_points.txt
wok_serve.egg-info/requires.txt
wok_serve.egg-info/top_level.txt
wok_serve/static/main.css
wok_serve/templates/layout.stpl