Metadata-Version: 2.1
Name: wok-serve
Version: 0.1.2
Summary: Tool to serve a directory of Wok files using a Notion-like template.
Home-page: https://gitlab.com/tijlvdb/wok-serve
Author: Tijl Van den Brugghen
Author-email: me@tijlvdb.me
License: MIT
Platform: UNKNOWN
Classifier: License :: OSI Approved :: MIT License
Classifier: Development Status :: 1 - Planning
Classifier: Programming Language :: Python :: 3
